<annotation>
	<folder>train</folder>
	<filename>car (35).jpeg</filename>
	<path>C:\Users\sulai\Videos\license\models\object_detection\data\images\train\car (35).jpeg</path>
	<source>
		<database>Unknown</database>
	</source>
	<size>
		<width>810</width>
		<height>1080</height>
		<depth>3</depth>
	</size>
	<segmented>0</segmented>
	<object>
		<name>license plate</name>
		<pose>Unspecified</pose>
		<truncated>0</truncated>
		<difficult>0</difficult>
		<bndbox>
			<xmin>317</xmin>
			<ymin>612</ymin>
			<xmax>491</xmax>
			<ymax>705</ymax>
		</bndbox>
	</object>
</annotation>
