<annotation>
	<folder>train</folder>
	<filename>kr32.jpg</filename>
	<path>C:\Users\sulai\Videos\license\models\object_detection\data\images\train\kr32.jpg</path>
	<source>
		<database>Unknown</database>
	</source>
	<size>
		<width>1000</width>
		<height>538</height>
		<depth>3</depth>
	</size>
	<segmented>0</segmented>
	<object>
		<name>license plate</name>
		<pose>Unspecified</pose>
		<truncated>0</truncated>
		<difficult>0</difficult>
		<bndbox>
			<xmin>475</xmin>
			<ymin>408</ymin>
			<xmax>606</xmax>
			<ymax>471</ymax>
		</bndbox>
	</object>
</annotation>
